{
  "schemaVersion": 1,
  "id": "xps_additions",
  "version": "${version}",

  "name": "XP Obelisk Additions",
  "description": "This mod add useful things to the XP Obelisk!",
  "authors": [
    "Meridanus"
  ],
  "contact": {
    "homepage": "https://www.curseforge.com/minecraft/mc-mods/xp-obelisk-additions",
    "sources": "https://github.com/Meridanus/fabric_xp_storage_additions"
  },

  "license": "MIT",
  "icon": "assets/xps_additions/icon.png",

  "environment": "*",
  "entrypoints": {
    "main": [
      "com.notker.xps_additions.XpsAdditions"
    ],
    "client": [
      "com.notker.xps_additions.XpsAdditionsClient"
    ]
  },
  "mixins": ["xp_obelisk_additions_mixin.json"],

  "depends": {
    "fabricloader": ">=0.14.17",
    "fabric": "*",
    "minecraft": "1.19.4",
    "java": ">=17"
  }
}
